binance/__init__.py
binance/apis/__init__.py
binance/apis/rest.py
binance/apis/wapi.py
binance/client/__init__.py
binance/client/base.py
binance/common/__init__.py
binance/common/constants.py
binance/common/exceptions.py
binance/common/sequenced_list.py
binance/common/types.py
binance/common/utils.py
binance/handlers/__init__.py
binance/handlers/base.py
binance/handlers/handlers.py
binance/handlers/orderbook.py
binance/handlers/orderbook_handler.py
binance/handlers/user_handlers.py
binance/processors/__init__.py
binance/processors/base.py
binance/processors/processors.py
binance/processors/user_processor.py
binance/subscribe/__init__.py
binance/subscribe/handler_context.py
binance/subscribe/manager.py
binance/subscribe/stream.py
binance_sdk-2.2.2.dist-info/licenses/LICENSE
binance_sdk-2.2.2.dist-info/METADATA
binance_sdk-2.2.2.dist-info/WHEEL
binance_sdk-2.2.2.dist-info/top_level.txt
binance_sdk-2.2.2.dist-info/RECORD
